oarepo_file_pipeline/__init__.py
oarepo_file_pipeline/config.py
oarepo_file_pipeline/ext.py
oarepo_file_pipeline/pipeline_registry.py
oarepo_file_pipeline/proxies.py
oarepo_file_pipeline/schemas.py
oarepo_file_pipeline/model/__init__.py
oarepo_file_pipeline/model/presets/__init__.py
oarepo_file_pipeline/model/presets/pipeline/__init__.py
oarepo_file_pipeline/model/presets/pipeline/resources/__init__.py
oarepo_file_pipeline/model/presets/pipeline/resources/config.py
oarepo_file_pipeline/model/presets/pipeline/resources/resource.py
oarepo_file_pipeline/model/presets/pipeline/services/__init__.py
oarepo_file_pipeline/model/presets/pipeline/services/components.py
oarepo_file_pipeline/model/presets/pipeline/services/pipeline_transfer.py
oarepo_file_pipeline/model/presets/pipeline/services/service.py
oarepo_file_pipeline/pipeline_generators/__init__.py
oarepo_file_pipeline/pipeline_generators/crypt4gh.py
oarepo_file_pipeline/pipeline_generators/image.py
oarepo_file_pipeline/pipeline_generators/zip.py
oarepo_file_pipeline-0.1.1.dist-info/METADATA
oarepo_file_pipeline-0.1.1.dist-info/WHEEL
oarepo_file_pipeline-0.1.1.dist-info/entry_points.txt
oarepo_file_pipeline-0.1.1.dist-info/licenses/LICENSE
oarepo_file_pipeline-0.1.1.dist-info/RECORD
