Metadata-Version: 2.4
Name: oarepo-file-pipeline
Version: 0.1.1
Summary: File pipeline
Project-URL: Homepage, https://github.com/oarepo/oarepo-file-pipeline
Author-email: Arsenii Pogodin <xsenyaaax@gmail.com>
License-File: LICENSE
Requires-Python: <3.15,>=3.13
Requires-Dist: joserfc
Requires-Dist: oarepo-model<1.0.0,>=0.1.0dev17
Requires-Dist: oarepo-runtime<3.0.0,>=2.0.0dev5
Requires-Dist: oarepo[rdm,tests]<15.0.0,>=14.0.0
Provides-Extra: oarepo14
Requires-Dist: oarepo[rdm]<15,>=14; extra == 'oarepo14'
Provides-Extra: tests
Requires-Dist: deepmerge; extra == 'tests'
Requires-Dist: pytest-invenio; extra == 'tests'
Requires-Dist: pytest-oarepo; extra == 'tests'
